README.md
setup.cfg
setup.py
taliabeez/__init__.py
taliabeez.egg-info/PKG-INFO
taliabeez.egg-info/SOURCES.txt
taliabeez.egg-info/dependency_links.txt
taliabeez.egg-info/requires.txt
taliabeez.egg-info/top_level.txt