Metadata-Version: 1.2
Name: taliabeez
Version: 0.1.2
Summary: TaliaBee ZigBee interface
Home-page: https://github.com/beyaznet/python-taliabeez-module
Author: Beyaz R&D Team
Author-email: arge@beyaz.net
License: MIT
Keywords: raspberry pi medioex taliabee zigbee xbee
Platform: UNKNOWN
Classifier: Development Status :: 4 - Beta
Classifier: Intended Audience :: Developers
Classifier: License :: OSI Approved :: MIT License
Classifier: Programming Language :: Python :: 3
Requires-Python: >=3
